joinpdf/__init__.py
joinpdf/cli.py
joinpdf-0.1.0.dist-info/entry_points.txt
joinpdf-0.1.0.dist-info/WHEEL
joinpdf-0.1.0.dist-info/METADATA
joinpdf-0.1.0.dist-info/RECORD
